setup.py
inspirespeech/__init__.py
inspirespeech/common.py
inspirespeech/config.py
inspirespeech/edit_distance.py
inspirespeech/htk.py
inspirespeech/htk_model.py
inspirespeech/htk_model_parser.py
inspirespeech/htk_model_utils.py
inspirespeech.egg-info/PKG-INFO
inspirespeech.egg-info/SOURCES.txt
inspirespeech.egg-info/dependency_links.txt
inspirespeech.egg-info/requires.txt
inspirespeech.egg-info/top_level.txt