Metadata-Version: 1.1
Name: inspirespeech
Version: 1.0.10
Summary: Helper library to participate in the INSPIRE challenge
Home-page: https://github.com/rikrd/inspire
Author: Ricard Marxer
Author-email: r.marxer@sheffield.ac.uk
License: UNKNOWN
Keywords: intelligibility,speech,evaluation
Platform: UNKNOWN
Classifier: Programming Language :: Python
Classifier: Development Status :: 4 - Beta
Classifier: Environment :: Other Environment
Classifier: Intended Audience :: Developers
Classifier: License :: OSI Approved :: GNU Library or Lesser General Public License (LGPL)
Classifier: Operating System :: OS Independent
Classifier: Topic :: Software Development :: Libraries :: Python Modules
Classifier: Topic :: Text Processing :: Linguistic
Requires: numpy
Requires: docopt
Requires: grako
Requires: progressbar_ipython
Requires: requests
